{
  "main": {
    "id": "19ea8e4614375f92",
    "type": "split",
    "children": [
      {
        "id": "32c98e148bcd4851",
        "type": "tabs",
        "children": [
          {
            "id": "2273e37314822899",
            "type": "leaf",
            "state": {
              "type": "markdown",
              "state": {
                "file": "Process/Journal.md",
                "mode": "source",
                "source": false
              }
            }
          }
        ]
      }
    ],
    "direction": "vertical"
  },
  "left": {
    "id": "456530968d86c87a",
    "type": "split",
    "children": [
      {
        "id": "080a756467364b1c",
        "type": "tabs",
        "children": [
          {
            "id": "0bfd67d89c7d85a0",
            "type": "leaf",
            "state": {
              "type": "file-explorer",
              "state": {
                "sortOrder": "alphabetical"
              }
            }
          },
          {
            "id": "772fcb2db7966eb2",
            "type": "leaf",
            "state": {
              "type": "search",
              "state": {
                "query": "",
                "matchingCase": false,
                "explainSearch": false,
                "collapseAll": false,
                "extraContext": false,
                "sortOrder": "alphabetical"
              }
            }
          },
          {
            "id": "d2d895771ca3fc01",
            "type": "leaf",
            "state": {
              "type": "bookmarks",
              "state": {}
            }
          }
        ]
      }
    ],
    "direction": "horizontal",
    "width": 300
  },
  "right": {
    "id": "0cdc1a652931c15b",
    "type": "split",
    "children": [
      {
        "id": "7344bc7281694da3",
        "type": "tabs",
        "children": [
          {
            "id": "ecdac562e632baa3",
            "type": "leaf",
            "state": {
              "type": "backlink",
              "state": {
                "file": "Process/Journal.md",
                "collapseAll": false,
                "extraContext": false,
                "sortOrder": "alphabetical",
                "showSearch": false,
                "searchQuery": "",
                "backlinkCollapsed": false,
                "unlinkedCollapsed": true
              }
            }
          },
          {
            "id": "2c44039203d43036",
            "type": "leaf",
            "state": {
              "type": "outgoing-link",
              "state": {
                "file": "Process/Journal.md",
                "linksCollapsed": false,
                "unlinkedCollapsed": true
              }
            }
          },
          {
            "id": "7f216a03bb6d11d4",
            "type": "leaf",
            "state": {
              "type": "tag",
              "state": {
                "sortOrder": "frequency",
                "useHierarchy": true
              }
            }
          },
          {
            "id": "cacbb80fb7d76eb3",
            "type": "leaf",
            "state": {
              "type": "outline",
              "state": {
                "file": "Process/Journal.md"
              }
            }
          }
        ]
      }
    ],
    "direction": "horizontal",
    "width": 300,
    "collapsed": true
  },
  "left-ribbon": {
    "hiddenItems": {
      "switcher:Open quick switcher": false,
      "graph:Open graph view": false,
      "canvas:Create new canvas": false,
      "daily-notes:Open today's daily note": false,
      "templates:Insert template": false,
      "command-palette:Open command palette": false
    }
  },
  "active": "2273e37314822899",
  "lastOpenFiles": [
    "examples/pawngTemplate/Temp/UnityTempFile-64612856bc04d463fac14a232206e29d",
    "examples/pawngTemplate/Temp/ADB-Refreshd2c27eff870bd4594a63c5fa822c3a96",
    "course-information/schedule.md",
    "examples/pawngTemplate/Library/ProtocolInstance.json",
    "examples/pawngTemplate/Temp/UnityTempFile-245155034bc0341d1a064119906b5522",
    "examples/pawngTemplate/Temp/ADB-Refreshdf2433c66684045a3bd99582c344cee0",
    "examples/pawngTemplate/Library/StateCache/SceneView/8b/8b3ad15c834d7c086f5246a7241600ca.json",
    "examples/pawngTemplate/Library/StateCache/SceneView/8b",
    "examples/pawngTemplate/Library/StateCache/MainStageHierarchy/67/67a23e9a55dff742bf9f7899e796e342.json",
    "examples/pawngTemplate/Library/StateCache/MainStageHierarchy/67",
    "examples/pawngTemplate/Library/Bee/backend_profiler0.traceevents",
    "examples/pawngTemplate/Library/Bee/TundraBuildState.state",
    "examples/pawngTemplate/Assets/Scripts/hearts.png",
    "course-information/resources.md",
    "examples/pawngTemplate/Assets/Sprites/hi.png",
    "examples/pawngTemplate/Assets/Sprites/paddle copy.png",
    "examples/pawngTemplate/Assets/Sprites/brick.png",
    "examples/pawngTemplate/Library/PackageCache/com.unity.burst@1.6.4/Documentation~/images/burst_aot_settings.png",
    "examples/pawngTemplate/Library/PackageCache/com.unity.burst@1.6.4/Documentation~/images/burst-noalias.png",
    "examples/pawngTemplate/Library/PackageCache/com.unity.burst@1.6.4/Documentation~/images/burst-noalias-vectorized.png",
    "examples/pawngTemplate/Library/PackageCache/com.unity.burst@1.6.4/Documentation~/images/burst-menu.png",
    "examples/pawngTemplate/Library/PackageCache/com.unity.burst@1.6.4/Documentation~/images/burst-inspector.png",
    "examples/pawngTemplate/Library/PackageCache/com.unity.burst@1.6.4/Documentation~/images/burst-alias.png",
    "examples/pawngTemplate/Library/PackageCache/com.unity.burst@1.6.4/Documentation~/docs/Warnings.md",
    "examples/pawngTemplate/Library/PackageCache/com.unity.burst@1.6.4/Documentation~/docs/StandalonePlayerSupport.md",
    "examples/pawngTemplate/Library/PackageCache/com.unity.burst@1.6.4/Documentation~/docs/QuickStart.md",
    "examples/pawngTemplate/Library/PackageCache/com.unity.burst@1.6.4/Documentation~/docs/OptimizationGuidelines-Aliasing.md",
    "examples/pawngTemplate/Library/PackageCache/com.unity.burst@1.6.4/Documentation~/docs/Presentations.md",
    "examples/pawngTemplate/Library/PackageCache/com.unity.burst@1.6.4/Documentation~/docs/OptimizationGuidelines.md",
    "examples/pawngTemplate/Library/PackageCache/com.unity.burst@1.6.4/Documentation~/docs/ModdingSupport.md",
    "examples/pawngTemplate/Library/PackageCache/com.unity.burst@1.6.4/Documentation~/docs/KnownIssues.md",
    "examples/pawngTemplate/Library/PackageCache/com.unity.burst@1.6.4/Documentation~/docs/DebuggingAndProfiling.md",
    "examples/pawngTemplate/Library/PackageCache/com.unity.burst@1.6.4/Documentation~/docs/CSharpLanguageSupport_Types.md",
    "examples/pawngTemplate/Library/PackageCache/com.unity.burst@1.6.4/Documentation~/docs/CSharpLanguageSupport_BurstIntrinsics.md",
    "examples/pawngTemplate/Library/PackageCache/com.unity.burst@1.6.4/Documentation~/docs/CSharpLanguageSupport_Lang.md",
    "examples/pawngTemplate/Library/PackageCache/com.unity.burst@1.6.4/Documentation~/docs/CSharpLanguageSupport_Intrinsics.md",
    "examples/pawngTemplate/Library/PackageCache/com.unity.burst@1.6.4/Documentation~/docs/AdvancedUsages.md",
    "examples/pawngTemplate/Library/PackageCache/com.unity.burst@1.6.4/Documentation~/index.md",
    "examples/pawngTemplate/Library/PackageCache/com.unity.burst@1.6.4/Documentation~/TableOfContents.md",
    "examples/pawngTemplate/Library/PackageCache/com.unity.burst@1.6.4/Third Party Notices.md",
    "examples/pawngTemplate/Library/PackageCache/com.unity.burst@1.6.4/LICENSE.md",
    "examples/pawngTemplate/Library/PackageCache/com.unity.burst@1.6.4/CHANGELOG.md",
    "examples/pawngTemplate/Library/PackageCache/com.unity.collab-proxy@1.15.13/Editor/Collaborate/Assets/Icons/README.md",
    "examples/pawngTemplate/Library/PackageCache/com.unity.collab-proxy@1.15.13/Editor/Collaborate/Views/README.md",
    "examples/pawngTemplate/Library/PackageCache/com.unity.collab-proxy@1.15.13/Editor/Collaborate/Utilities/README.md",
    "examples/pawngTemplate/Library/PackageCache/com.unity.collab-proxy@1.15.13/Editor/Collaborate/UserInterface/README.md"
  ]
}